rst2gfm/__init__.py
rst2gfm/main.py
rst2gfm-0.1.2.dist-info/LICENSE
rst2gfm-0.1.2.dist-info/METADATA
rst2gfm-0.1.2.dist-info/WHEEL
rst2gfm-0.1.2.dist-info/entry_points.txt
rst2gfm-0.1.2.dist-info/top_level.txt
rst2gfm-0.1.2.dist-info/RECORD
