Metadata-Version: 2.2
Name: rst2gfm
Version: 0.1.2
Summary: A tool to convert reStructuredText to GitHub Flavored Markdown
Author-email: pdh <meafinc@gmail.com>
License: MIT
Project-URL: Homepage, https://github.com/pdh/rst2gfm
Project-URL: Bug Tracker, https://github.com/pdh/rst2gfm/issues
Classifier: Programming Language :: Python :: 3
Classifier: License :: OSI Approved :: MIT License
Classifier: Operating System :: OS Independent
Requires-Python: >=3.6
License-File: LICENSE
Requires-Dist: docutils>=0.17.1
